johnston_ttu/__init__.py
johnston_ttu/figures.py
johnston_ttu/helpers.py
johnston_ttu/processing.py
johnston_ttu-0.8.2.dist-info/METADATA
johnston_ttu-0.8.2.dist-info/WHEEL
johnston_ttu-0.8.2.dist-info/licenses/LICENSE
johnston_ttu-0.8.2.dist-info/RECORD
