Metadata-Version: 2.1
Name: johnston_ttu
Version: 0.8.2
Summary: A Python package for research done in the Johnston Group.
Project-URL: Homepage, https://github.com/pypa/sampleproject/
Author-email: Derek Johnston <derek.a.johnston@ttu.edu>
License-File: LICENSE
Classifier: License :: OSI Approved :: MIT License
Classifier: Operating System :: OS Independent
Classifier: Programming Language :: Python :: 3
Requires-Python: >=3.11
Requires-Dist: matplotlib
Requires-Dist: numpy
Requires-Dist: pandas
